{"3770.365031426024": "American bison", "1270.6248018142014": "American bison", "36800.69167026212": "Cattle (Domestic type)", "7292.864303935407": "Cattle (Domestic type)", "3856.958096483915": "Environmental", "226.03597380355205": "Cattle (Domestic type)", "3812.275850229545": "Caribou", "3155.1193721067034": "Caribou", "5996.784650275288": "Caribou", "14340.579660260955": "Cliff Chipmunk", "7910.456208426957": "Cliff Chipmunk", "7475.526733207904": "Cliff Chipmunk", "2029.6095189299322": "Eastern Chipmunk", "13295.18222951927": "Eastern Chipmunk", "348.23705241394606": "Eastern Chipmunk", "12328.465164834495": "Eastern Chipmunk", "13965.633079590314": "Eastern Chipmunk", "11400.278697038224": "Eastern Chipmunk", "23835.308584416605": "Eastern Chipmunk", "13259.636725512604": "Eastern Chipmunk", "7127.8926598012085": "White-nosed Coati", "17463.182187227903": "White-nosed Coati", "5993.828253633284": "Coyote", "2287.0793890722057": "Coyote", "8902.697235782682": "Coyote", "2867.693510990225": "Coyote", "6226.7995333274675": "Coyote", "2094.5476981761744": "Coyote", "6675.804226085305": "Coyote", "3659.013966825304": "Coyote", "7092.03673826223": "Mule Deer", "1170.9548283057636": "Mule Deer", "9449.950920220721": "White-tailed Deer", "1511.1141099564818": "White-tailed Deer", "1946.283730360779": "White-tailed Deer", "626.1526258167174": "Dog (Domestic type)", "2188.4885772977823": "Dog (Domestic type)", "5558.763403993056": "Dog (Domestic type)", "8821.31496479984": "Dog (Domestic type)", "6382.506228661909": "Dog (Domestic type)", "20131.870170705217": "Dog (Domestic type)", "1987.180024884146": "Dog (Domestic type)", "355.949703640994": "Dog (Domestic type)", "5635.500034641823": "Dog (Domestic type)", "7254.545339817332": "Dog (Domestic type)", "1549.9392447894134": "Dog (Domestic type)", "7971.287238911583": "Arizona black-tailed prairie dog", "13032.625278800997": "Red Deer", "7359.3394889278115": "Red Deer", "9970.32457496461": "Red Deer", "2864.9823693040767": "Green-and-rufous Kingfisher", "22756.410177812322": "Chattering Gnatwren", "15318.940859386623": "Bolivian Warbling-Finch", "14514.331769770328": "Black-hooded Sunbeam", "2503.740064961235": "Hooded Mountain-Toucan", "7154.462525711516": "Brown Violetear", "4939.328683120054": "Slaty Gnateater", "11571.376641197272": "Cream-winged Cinclodes", "13373.0176955814": "Diademed Tapaculo", "17954.81225473909": "Band-tailed Seedeater", "2451.87812622461": "Gray-bellied Flowerpiercer", "13000.637656826348": "Rufous-bellied Mountain-Tanager", "5217.567308975624": "Rufous-rumped Foliage-gleaner", "7184.469657871079": "Northern Barred-Woodcreeper", "1272.9751456580063": "Black-banded Woodcreeper (Black-banded)", "2545.7093392406737": "Black-banded Woodcreeper (Black-banded)", "13901.66586613843": "Black-banded Woodcreeper (Black-banded)", "1301.4885934538431": "Black-banded Woodcreeper (Black-banded)", "10814.471855291029": "Black-banded Woodcreeper (Spot-throated)", "7285.78703788317": "Black-banded Woodcreeper (Black-banded)", "443.5513421206561": "Black-banded Woodcreeper (Spot-throated)", "9821.758785666938": "Black-banded Woodcreeper (Spot-throated)", "2526.132029380918": "Black-banded Woodcreeper (Spot-throated)", "7895.12223616925": "Black-banded Woodcreeper (Spot-throated)", "7017.7057498969725": "Black-banded Woodcreeper (Spot-throated)", "21404.443724580648": "Black-banded Woodcreeper (Spot-throated)", "14079.09067366394": "Black-banded Woodcreeper (Spot-throated)", "991.5488357215627": "Black-banded Woodcreeper (Spot-throated)", "12768.422062789521": "Black-banded Woodcreeper (Spot-throated)", "10219.376483880802": "Black-banded Woodcreeper (Spot-throated)", "3244.669852561361": "Black-banded Woodcreeper (Spot-throated)", "2498.0874301111335": "Black-banded Woodcreeper (Black-banded)", "8463.204043615844": "Black-banded Woodcreeper (Spot-throated)", "3894.314007434741": "Black-banded Woodcreeper (Black-banded)", "3793.1639405885085": "Black-banded Woodcreeper (Spot-throated)", "32054.77804454486": "Black-banded Woodcreeper (Spot-throated)", "1258.2161071057158": "Strong-billed Woodcreeper (Andean Northern)", "1469.0204937960632": "Strong-billed Woodcreeper (Andean Northern)", "395.78594352082536": "Strong-billed Woodcreeper (Andean Northern)", "5422.723770540543": "Strong-billed Woodcreeper (Andean Northern)", "14919.92031381113": "Strong-billed Woodcreeper (Andean Northern)", "3304.026849702468": "Strong-billed Woodcreeper (Andean Northern)", "3642.2319948824966": "Strong-billed Woodcreeper (Andean Northern)", "14660.621798773447": "Strong-billed Woodcreeper (Andean Northern)", "2957.2227434260617": "Strong-billed Woodcreeper (Andean Northern)", "8362.559782136615": "Strong-billed Woodcreeper (Andean Northern)", "4385.295368436846": "Strong-billed Woodcreeper (Andean Northern)", "8330.212535085224": "Strong-billed Woodcreeper (Andean Northern)", "6644.851363329736": "Strong-billed Woodcreeper (Andean Northern)", "1045.389905981075": "Strong-billed Woodcreeper (Andean Northern)", "10102.31324917482": "Ochraceous Bulbul", "4699.575586850782": "Bornean Whistling-Thrush", "17048.70117025007": "Bornean Whistling-Thrush", "10738.524396399927": "Chestnut-hooded Laughingthrush", "5686.9133361339445": "Bornean Treepie", "13331.02243882241": "White-throated Fantail", "21825.037809747": "Ochraceous Bulbul", "10599.788670700216": "Bornean Green-Magpie", "12612.222583277266": "Ochraceous Bulbul", "25590.088087576507": "Bare-headed Laughingthrush", "18171.399136665466": "Bare-headed Laughingthrush", "1232.3264061385296": "Bare-headed Laughingthrush", "7616.4399108465395": "Black-and-crimson Oriole", "18681.523169065684": "Mountain Tailorbird", "16868.054881312066": "Sunda Bush Warbler", "24297.97591458504": "Mountain Leaf Warbler", "3995.669555810959": "White-browed Shortwing", "5994.7978008157215": "Whitehead's Trogon", "10422.804539343635": "Bornean Green-Magpie", "4660.516086897211": "Golden-naped Barbet", "9745.87994079469": "Whitehead's Broadbill", "25158.186746095325": "Golden-naped Barbet", "6902.407782669031": "Crimson-headed Partridge", "16977.16585199484": "Golden-naped Barbet", "12844.88836677038": "Maroon Woodpecker", "7231.144690959707": "Bare-headed Laughingthrush", "13459.047176403192": "Maroon Woodpecker", "14243.276440340473": "Sunda Laughingthrush", "16299.871572300235": "Maroon Woodpecker", "10012.377195181374": "Whitehead's Trogon", "23838.23835563296": "Bornean Treepie", "6425.154542806156": "Red-breasted Partridge", "9542.084242604918": "Crimson Sunbird (Crimson)", "6222.726553184461": "Little Pied Flycatcher", "6167.395019966163": "Blyth's Shrike-Babbler", "6521.512331474822": "Mountain Scops-Owl", "23030.666889558473": "Rufous-tailed Tailorbird", "29955.20350807316": "Blue-eared Barbet", "23388.890358589273": "Black-and-red Broadbill", "23122.255084219676": "Blue-eared Barbet", "11092.638173798496": "Black-headed Bulbul", "23419.007252633855": "Brachypodius Rubigula Pycnonotus sp ", "20656.841163435634": "White-rumped Shama (White-crowned)", "21125.162819615412": "White-rumped Shama (White-crowned)", "10323.626646948798": "frog toad sp ", "9811.50704033386": "Bold-striped Tit-Babbler", "17833.848044990693": "Rufous-tailed Tailorbird", "18163.480470805196": "Bushy-crested Hornbill", "20136.13634922438": "Bushy-crested Hornbill", "11624.284858970206": "Chestnut-winged Babbler", "16570.295545724446": "Many-colored Rush Tyrant", "21863.691826551905": "White-browed Chat-Tyrant", "6811.507755403163": "Plumbeous Rail", "11341.15039863777": "Speckle-breasted Wren (Speckle-breasted)", "4232.437611996849": "Gray-and-gold Warbler", "12626.057623722063": "Mountain Wren", "21378.347767296757": "Ochraceous Attila", "9107.157373964206": "Slaty Antwren", "7901.731078337974": "wren sp ", "5572.152934340328": "Crested Guan", "21295.827879523797": "spadebill sp ", "12428.917090250063": "Lesser Greenlet (Gray-headed)", "43358.67308665355": "Ruddy Pigeon (Berlepsch's)", "13714.010571482675": "Gray-and-gold Warbler", "2847.2428103071156": "Espa\u00f1ola Ground-Finch", "9659.953937365975": "Espa\u00f1ola Ground-Finch", "2759.8769345664286": "Espa\u00f1ola Ground-Finch", "153.29826393723064": "Espa\u00f1ola Ground-Finch", "365.19815347286493": "Espa\u00f1ola Ground-Finch", "197.9421916209646": "Espa\u00f1ola Ground-Finch", "471.1471483612628": "Espa\u00f1ola Ground-Finch", "13121.231354665086": "Espa\u00f1ola Ground-Finch", "385.8844724297358": "Espa\u00f1ola Ground-Finch", "1720.0221142054736": "Espa\u00f1ola Ground-Finch", "3208.81722353864": "Espa\u00f1ola Ground-Finch", "19426.263908826346": "Espa\u00f1ola Ground-Finch", "654.5268278031429": "Espa\u00f1ola Ground-Finch", "1006.6733434790059": "Espa\u00f1ola Ground-Finch", "4600.571507225223": "Espa\u00f1ola Ground-Finch", "8309.73731144069": "Espa\u00f1ola Ground-Finch", "6288.22302576156": "Espa\u00f1ola Ground-Finch", "774.5744185245081": "Gray Warbler-Finch", "12786.17258671971": "Gray Warbler-Finch", "1369.650123497336": "Gray Warbler-Finch", "10481.244481657137": "Gray Warbler-Finch", "1996.230081306496": "Gray Warbler-Finch", "5614.676410725155": "Gray Warbler-Finch", "5358.899009017788": "Gray Warbler-Finch", "611.2048089182814": "Espa\u00f1ola Ground-Finch", "624.8722406773239": "Espa\u00f1ola Ground-Finch", "10685.83342905984": "Espa\u00f1ola Ground-Finch", "349.36586330881033": "Espa\u00f1ola Ground-Finch", "530.3277087441825": "Espa\u00f1ola Ground-Finch", "1033.5943134914337": "Espa\u00f1ola Ground-Finch", "3844.3705674283324": "Espa\u00f1ola Ground-Finch", "391.1502078019798": "Espa\u00f1ola Ground-Finch", "3270.378889411729": "Espa\u00f1ola Ground-Finch", "7681.195775369347": "Espa\u00f1ola Ground-Finch", "1408.0536680538814": "Gray Warbler-Finch", "12663.073649954682": "Gray Warbler-Finch", "25316.259061203164": "Red Fody", "7213.156243546259": "Greater Lesser Vasa Parrot", "13385.4047425823": "Souimanga Sunbird (Yellow-bellied)", "6801.888485763691": "Plain Martin", "4153.696286783268": "Stripe-throated Jery", "2338.3344089438892": "bamboo lemur", "1765.3240529826596": "Environmental", "3422.3760220565364": "Crested Drongo", "7044.003551357635": "Tylas Vanga (Eduard's)", "5495.783425373776": "Environmental", "3489.997529855182": "Souimanga Sunbird (Yellow-bellied)", "14340.752662209787": "Tylas Vanga (Eduard's)", "13698.950307417128": "Madagascar Paradise-Flycatcher", "6816.692964517001": "Madagascar Magpie-Robin (White-bellied)", "2653.8339482228644": "Tylas Vanga (Eduard's)", "11711.215976874002": "Madagascar Bulbul", "11585.99917374693": "Crested Drongo", "13798.342321408345": "Green Jery", "8589.785082392607": "Common Newtonia", "4935.000163968275": "Yellow-browed Oxylabes", "13117.322908102022": "Pitta-like Ground-Roller", "17025.79603874461": "Madagascar Brush-Warbler", "11181.691575959281": "Madagascar Brush-Warbler", "12657.471988868216": "Madagascar Brush-Warbler", "16601.276801856387": "Long-billed Bernieria", "18981.423737366767": "ruffed lemur", "8330.488422773327": "Madagascar Brush-Warbler", "1550.7989575560634": "White-throated Rail", "12396.56209273161": "Madagascar Starling", "7171.193969004952": "Tylas Vanga (Eduard's)", "13003.579463591186": "Rand's Warbler", "9952.092330373573": "Red-tailed Vanga", "6144.02232837446": "indri", "10341.873866925704": "Tylas Vanga (Eduard's)", "17522.291515320678": "bird sp ", "3899.058236417688": "Red-fronted Coua", "7216.265278864817": "Short-legged Ground-Roller", "1256.5592268983567": "Red-breasted Coua", "17709.92571811367": "Madagascar Owl", "9326.021834853396": "Rand's Warbler", "19783.539000239045": "Frances's Sparrowhawk", "16733.428671565416": "Cryptic Warbler", "25091.637708522478": "Brown Emutail", "5310.512146806487": "Madagascar Hoopoe", "6622.727211822062": "Gray-headed Lovebird", "3979.255385182479": "Stripe-throated Jery", "17905.617907540658": "Subdesert Brush-Warbler", "14477.223137105382": "Gray-headed Lovebird", "4836.2764909276975": "diurnal raptor sp ", "6406.356198316972": "Sickle-billed Vanga"}